<?xml version="1.0" standalone="yes"?>
<mPortal>
  <xs:schema id="mPortal" xmlns="" xmlns:xs="http://www.w3.org/2001/XMLSchema" xmlns:msdata="urn:schemas-microsoft-com:xml-msdata">
    <xs:element name="mPortal" msdata:IsDataSet="true" msdata:UseCurrentLocale="true">
      <xs:complexType>
        <xs:choice minOccurs="0" maxOccurs="unbounded">
          <xs:element name="MCCandidate">
            <xs:complexType>
              <xs:sequence>
                <xs:element name="Id" msdata:ReadOnly="true" msdata:AutoIncrement="true" type="xs:int" />
                <xs:element name="Name">
                  <xs:simpleType>
                    <xs:restriction base="xs:string">
                      <xs:maxLength value="250" />
                    </xs:restriction>
                  </xs:simpleType>
                </xs:element>
                <xs:element name="Entry">
                  <xs:simpleType>
                    <xs:restriction base="xs:string">
                      <xs:maxLength value="2000" />
                    </xs:restriction>
                  </xs:simpleType>
                </xs:element>
                <xs:element name="Lyrics">
                  <xs:simpleType>
                    <xs:restriction base="xs:string">
                      <xs:maxLength value="2147483647" />
                    </xs:restriction>
                  </xs:simpleType>
                </xs:element>
                <xs:element name="SourceUrl">
                  <xs:simpleType>
                    <xs:restriction base="xs:string">
                      <xs:maxLength value="500" />
                    </xs:restriction>
                  </xs:simpleType>
                </xs:element>
                <xs:element name="SourceUrl2">
                  <xs:simpleType>
                    <xs:restriction base="xs:string">
                      <xs:maxLength value="500" />
                    </xs:restriction>
                  </xs:simpleType>
                </xs:element>
                <xs:element name="Lyricist">
                  <xs:simpleType>
                    <xs:restriction base="xs:string">
                      <xs:maxLength value="250" />
                    </xs:restriction>
                  </xs:simpleType>
                </xs:element>
                <xs:element name="Interpreter">
                  <xs:simpleType>
                    <xs:restriction base="xs:string">
                      <xs:maxLength value="250" />
                    </xs:restriction>
                  </xs:simpleType>
                </xs:element>
                <xs:element name="PhotoFile">
                  <xs:simpleType>
                    <xs:restriction base="xs:string">
                      <xs:maxLength value="500" />
                    </xs:restriction>
                  </xs:simpleType>
                </xs:element>
                <xs:element name="CompetitionId" type="xs:int" />
                <xs:element name="Rank" type="xs:int" />
                <xs:element name="WinnerRank" type="xs:int" />
              </xs:sequence>
            </xs:complexType>
          </xs:element>
        </xs:choice>
      </xs:complexType>
      <xs:unique name="Constraint1" msdata:PrimaryKey="true">
        <xs:selector xpath=".//MCCandidate" />
        <xs:field xpath="Id" />
      </xs:unique>
    </xs:element>
  </xs:schema>
</mPortal>